{
  "mod_name": "Magic Bag",
  "mod_type": "vehicle",
  "current_version": 1,
  "scripts": [
    {
      "file": "main.lua",
      "lines": 186,
      "callbacks_found": [
        "init",
        "GetAimPos",
        "PickItem",
        "ThrowItem",
        "tick",
        "draw"
      ],
      "api_calls": [
        {
          "function": "RegisterTool",
          "line": 2,
          "domain": "server",
          "needs_player_id": false,
          "restricted_to": null,
          "deprecated": null
        },
        {
          "function": "SetBool",
          "line": 3,
          "domain": "both",
          "needs_player_id": false,
          "restricted_to": null,
          "deprecated": null
        },
        {
          "function": "SetFloat",
          "line": 4,
          "domain": "both",
          "needs_player_id": false,
          "restricted_to": null,
          "deprecated": null
        },
        {
          "function": "LoadSound",
          "line": 14,
          "domain": "client",
          "needs_player_id": false,
          "restricted_to": null,
          "deprecated": null
        },
        {
          "function": "LoadSound",
          "line": 15,
          "domain": "client",
          "needs_player_id": false,
          "restricted_to": null,
          "deprecated": null
        },
        {
          "function": "GetCameraTransform",
          "line": 19,
          "domain": "both",
          "needs_player_id": false,
          "restricted_to": null,
          "deprecated": null
        },
        {
          "function": "TransformToParentPoint",
          "line": 20,
          "domain": "both",
          "needs_player_id": false,
          "restricted_to": null,
          "deprecated": null
        },
        {
          "function": "Vec",
          "line": 20,
          "domain": "both",
          "needs_player_id": false,
          "restricted_to": null,
          "deprecated": null
        },
        {
          "function": "VecSub",
          "line": 21,
          "domain": "both",
          "needs_player_id": false,
          "restricted_to": null,
          "deprecated": null
        },
        {
          "function": "VecLength",
          "line": 22,
          "domain": "both",
          "needs_player_id": false,
          "restricted_to": null,
          "deprecated": null
        },
        {
          "function": "VecNormalize",
          "line": 23,
          "domain": "both",
          "needs_player_id": false,
          "restricted_to": null,
          "deprecated": null
        },
        {
          "function": "QueryRaycast",
          "line": 24,
          "domain": "both",
          "needs_player_id": false,
          "restricted_to": null,
          "deprecated": null
        },
        {
          "function": "TransformToParentPoint",
          "line": 26,
          "domain": "both",
          "needs_player_id": false,
          "restricted_to": null,
          "deprecated": null
        },
        {
          "function": "Vec",
          "line": 26,
          "domain": "both",
          "needs_player_id": false,
          "restricted_to": null,
          "deprecated": null
        },
        {
          "function": "GetCameraTransform",
          "line": 32,
          "domain": "both",
          "needs_player_id": false,
          "restricted_to": null,
          "deprecated": null
        },
        {
          "function": "VecSub",
          "line": 42,
          "domain": "both",
          "needs_player_id": false,
          "restricted_to": null,
          "deprecated": null
        },
        {
          "function": "GetShapeLocalTransform",
          "line": 54,
          "domain": "both",
          "needs_player_id": false,
          "restricted_to": null,
          "deprecated": null
        },
        {
          "function": "Transform",
          "line": 55,
          "domain": "both",
          "needs_player_id": false,
          "restricted_to": null,
          "deprecated": null
        },
        {
          "function": "Vec",
          "line": 55,
          "domain": "both",
          "needs_player_id": false,
          "restricted_to": null,
          "deprecated": null
        },
        {
          "function": "Vec",
          "line": 59,
          "domain": "both",
          "needs_player_id": false,
          "restricted_to": null,
          "deprecated": null
        },
        {
          "function": "TransformToParentVec",
          "line": 60,
          "domain": "both",
          "needs_player_id": false,
          "restricted_to": null,
          "deprecated": null
        },
        {
          "function": "GetBodyTransform",
          "line": 61,
          "domain": "both",
          "needs_player_id": false,
          "restricted_to": null,
          "deprecated": null
        },
        {
          "function": "SetBodyTransform",
          "line": 63,
          "domain": "both",
          "needs_player_id": false,
          "restricted_to": null,
          "deprecated": null
        },
        {
          "function": "Transform",
          "line": 63,
          "domain": "both",
          "needs_player_id": false,
          "restricted_to": null,
          "deprecated": null
        },
        {
          "function": "Quat",
          "line": 63,
          "domain": "both",
          "needs_player_id": false,
          "restricted_to": null,
          "deprecated": null
        },
        {
          "function": "PlaySound",
          "line": 68,
          "domain": "client",
          "needs_player_id": false,
          "restricted_to": null,
          "deprecated": null
        },
        {
          "function": "GetCameraTransform",
          "line": 76,
          "domain": "both",
          "needs_player_id": false,
          "restricted_to": null,
          "deprecated": null
        },
        {
          "function": "TransformToParentPoint",
          "line": 77,
          "domain": "both",
          "needs_player_id": false,
          "restricted_to": null,
          "deprecated": null
        },
        {
          "function": "Vec",
          "line": 77,
          "domain": "both",
          "needs_player_id": false,
          "restricted_to": null,
          "deprecated": null
        },
        {
          "function": "TransformToParentPoint",
          "line": 78,
          "domain": "both",
          "needs_player_id": false,
          "restricted_to": null,
          "deprecated": null
        },
        {
          "function": "Vec",
          "line": 78,
          "domain": "both",
          "needs_player_id": false,
          "restricted_to": null,
          "deprecated": null
        },
        {
          "function": "VecSub",
          "line": 79,
          "domain": "both",
          "needs_player_id": false,
          "restricted_to": null,
          "deprecated": null
        },
        {
          "function": "VecScale",
          "line": 80,
          "domain": "both",
          "needs_player_id": false,
          "restricted_to": null,
          "deprecated": null
        },
        {
          "function": "SetBodyTransform",
          "line": 83,
          "domain": "both",
          "needs_player_id": false,
          "restricted_to": null,
          "deprecated": null
        },
        {
          "function": "Transform",
          "line": 83,
          "domain": "both",
          "needs_player_id": false,
          "restricted_to": null,
          "deprecated": null
        },
        {
          "function": "SetBodyVelocity",
          "line": 86,
          "domain": "both",
          "needs_player_id": false,
          "restricted_to": null,
          "deprecated": null
        },
        {
          "function": "GetString",
          "line": 92,
          "domain": "both",
          "needs_player_id": false,
          "restricted_to": null,
          "deprecated": null
        },
        {
          "function": "GetPlayerVehicle",
          "line": 92,
          "domain": "server",
          "needs_player_id": true,
          "restricted_to": null,
          "deprecated": null
        },
        {
          "function": "InputPressed",
          "line": 93,
          "domain": "client",
          "needs_player_id": false,
          "restricted_to": null,
          "deprecated": null
        },
        {
          "function": "InputDown",
          "line": 98,
          "domain": "client",
          "needs_player_id": false,
          "restricted_to": null,
          "deprecated": null
        },
        {
          "function": "InputReleased",
          "line": 103,
          "domain": "client",
          "needs_player_id": false,
          "restricted_to": null,
          "deprecated": null
        },
        {
          "function": "PlaySound",
          "line": 108,
          "domain": "client",
          "needs_player_id": false,
          "restricted_to": null,
          "deprecated": null
        },
        {
          "function": "Transform",
          "line": 114,
          "domain": "both",
          "needs_player_id": false,
          "restricted_to": null,
          "deprecated": null
        },
        {
          "function": "Vec",
          "line": 114,
          "domain": "both",
          "needs_player_id": false,
          "restricted_to": null,
          "deprecated": null
        },
        {
          "function": "QuatEuler",
          "line": 114,
          "domain": "both",
          "needs_player_id": false,
          "restricted_to": null,
          "deprecated": null
        },
        {
          "function": "SetToolTransform",
          "line": 115,
          "domain": "server",
          "needs_player_id": false,
          "restricted_to": null,
          "deprecated": null
        },
        {
          "function": "Transform",
          "line": 118,
          "domain": "both",
          "needs_player_id": false,
          "restricted_to": null,
          "deprecated": null
        },
        {
          "function": "Vec",
          "line": 119,
          "domain": "both",
          "needs_player_id": false,
          "restricted_to": null,
          "deprecated": null
        },
        {
          "function": "QuatEuler",
          "line": 120,
          "domain": "both",
          "needs_player_id": false,
          "restricted_to": null,
          "deprecated": null
        },
        {
          "function": "SetToolTransform",
          "line": 121,
          "domain": "server",
          "needs_player_id": false,
          "restricted_to": null,
          "deprecated": null
        },
        {
          "function": "Transform",
          "line": 127,
          "domain": "both",
          "needs_player_id": false,
          "restricted_to": null,
          "deprecated": null
        },
        {
          "function": "Vec",
          "line": 128,
          "domain": "both",
          "needs_player_id": false,
          "restricted_to": null,
          "deprecated": null
        },
        {
          "function": "QuatEuler",
          "line": 129,
          "domain": "both",
          "needs_player_id": false,
          "restricted_to": null,
          "deprecated": null
        },
        {
          "function": "SetToolTransform",
          "line": 130,
          "domain": "server",
          "needs_player_id": false,
          "restricted_to": null,
          "deprecated": null
        },
        {
          "function": "InputValue",
          "line": 142,
          "domain": "client",
          "needs_player_id": false,
          "restricted_to": null,
          "deprecated": null
        },
        {
          "function": "InputValue",
          "line": 142,
          "domain": "client",
          "needs_player_id": false,
          "restricted_to": null,
          "deprecated": null
        },
        {
          "function": "Vec",
          "line": 144,
          "domain": "both",
          "needs_player_id": false,
          "restricted_to": null,
          "deprecated": null
        },
        {
          "function": "GetBodyAngularVelocity",
          "line": 145,
          "domain": "both",
          "needs_player_id": false,
          "restricted_to": null,
          "deprecated": null
        },
        {
          "function": "VecAdd",
          "line": 146,
          "domain": "both",
          "needs_player_id": false,
          "restricted_to": null,
          "deprecated": null
        },
        {
          "function": "SetBodyAngularVelocity",
          "line": 147,
          "domain": "both",
          "needs_player_id": false,
          "restricted_to": null,
          "deprecated": null
        },
        {
          "function": "GetString",
          "line": 157,
          "domain": "both",
          "needs_player_id": false,
          "restricted_to": null,
          "deprecated": null
        },
        {
          "function": "GetPlayerVehicle",
          "line": 157,
          "domain": "server",
          "needs_player_id": true,
          "restricted_to": null,
          "deprecated": null
        },
        {
          "function": "UiPush",
          "line": 158,
          "domain": "client",
          "needs_player_id": false,
          "restricted_to": "client.draw",
          "deprecated": null
        },
        {
          "function": "UiTranslate",
          "line": 159,
          "domain": "client",
          "needs_player_id": false,
          "restricted_to": "client.draw",
          "deprecated": null
        },
        {
          "function": "UiCenter",
          "line": 159,
          "domain": "client",
          "needs_player_id": false,
          "restricted_to": "client.draw",
          "deprecated": null
        },
        {
          "function": "UiHeight",
          "line": 159,
          "domain": "client",
          "needs_player_id": false,
          "restricted_to": "client.draw",
          "deprecated": null
        },
        {
          "function": "UiAlign",
          "line": 160,
          "domain": "client",
          "needs_player_id": false,
          "restricted_to": "client.draw",
          "deprecated": null
        },
        {
          "function": "UiColor",
          "line": 161,
          "domain": "client",
          "needs_player_id": false,
          "restricted_to": "client.draw",
          "deprecated": null
        },
        {
          "function": "UiFont",
          "line": 162,
          "domain": "client",
          "needs_player_id": false,
          "restricted_to": "client.draw",
          "deprecated": null
        },
        {
          "function": "UiText",
          "line": 164,
          "domain": "client",
          "needs_player_id": false,
          "restricted_to": "client.draw",
          "deprecated": null
        },
        {
          "function": "UiPop",
          "line": 165,
          "domain": "client",
          "needs_player_id": false,
          "restricted_to": "client.draw",
          "deprecated": null
        },
        {
          "function": "UiPush",
          "line": 167,
          "domain": "client",
          "needs_player_id": false,
          "restricted_to": "client.draw",
          "deprecated": null
        },
        {
          "function": "UiTranslate",
          "line": 168,
          "domain": "client",
          "needs_player_id": false,
          "restricted_to": "client.draw",
          "deprecated": null
        },
        {
          "function": "UiCenter",
          "line": 168,
          "domain": "client",
          "needs_player_id": false,
          "restricted_to": "client.draw",
          "deprecated": null
        },
        {
          "function": "UiHeight",
          "line": 168,
          "domain": "client",
          "needs_player_id": false,
          "restricted_to": "client.draw",
          "deprecated": null
        },
        {
          "function": "UiColor",
          "line": 169,
          "domain": "client",
          "needs_player_id": false,
          "restricted_to": "client.draw",
          "deprecated": null
        },
        {
          "function": "UiFont",
          "line": 170,
          "domain": "client",
          "needs_player_id": false,
          "restricted_to": "client.draw",
          "deprecated": null
        },
        {
          "function": "UiText",
          "line": 172,
          "domain": "client",
          "needs_player_id": false,
          "restricted_to": "client.draw",
          "deprecated": null
        },
        {
          "function": "UiTranslate",
          "line": 174,
          "domain": "client",
          "needs_player_id": false,
          "restricted_to": "client.draw",
          "deprecated": null
        },
        {
          "function": "UiColor",
          "line": 175,
          "domain": "client",
          "needs_player_id": false,
          "restricted_to": "client.draw",
          "deprecated": null
        },
        {
          "function": "UiImageBox",
          "line": 177,
          "domain": "client",
          "needs_player_id": false,
          "restricted_to": "client.draw",
          "deprecated": null
        },
        {
          "function": "UiTranslate",
          "line": 179,
          "domain": "client",
          "needs_player_id": false,
          "restricted_to": "client.draw",
          "deprecated": null
        },
        {
          "function": "UiColor",
          "line": 181,
          "domain": "client",
          "needs_player_id": false,
          "restricted_to": "client.draw",
          "deprecated": null
        },
        {
          "function": "UiImageBox",
          "line": 182,
          "domain": "client",
          "needs_player_id": false,
          "restricted_to": "client.draw",
          "deprecated": null
        },
        {
          "function": "UiPop",
          "line": 184,
          "domain": "client",
          "needs_player_id": false,
          "restricted_to": "client.draw",
          "deprecated": null
        }
      ],
      "server_calls": 6,
      "client_calls": 32,
      "ambiguous_calls": 47,
      "deprecated_calls": [],
      "entity_handle_checks": [
        {
          "line": 99,
          "content": "if count < 2 or rottimer > 0 then return end"
        },
        {
          "line": 104,
          "content": "if count < 2 or rottimer > 0 then return end"
        },
        {
          "line": 117,
          "content": "if swingTimer > 0 then"
        },
        {
          "line": 126,
          "content": "if pickTimer > 0 then"
        },
        {
          "line": 140,
          "content": "if rottimer > 0 then"
        }
      ],
      "registry_usage": [
        {
          "function": "SetBool",
          "line": 3,
          "domain": "both",
          "needs_player_id": false,
          "restricted_to": null,
          "deprecated": null
        },
        {
          "function": "SetFloat",
          "line": 4,
          "domain": "both",
          "needs_player_id": false,
          "restricted_to": null,
          "deprecated": null
        },
        {
          "function": "GetString",
          "line": 92,
          "domain": "both",
          "needs_player_id": false,
          "restricted_to": null,
          "deprecated": null
        },
        {
          "function": "GetString",
          "line": 157,
          "domain": "both",
          "needs_player_id": false,
          "restricted_to": null,
          "deprecated": null
        }
      ]
    }
  ],
  "complexity": "simple",
  "estimated_approach": "template",
  "issues": [
    "Handle check at main.lua:99: if count < 2 or rottimer > 0 then return end",
    "Handle check at main.lua:104: if count < 2 or rottimer > 0 then return end",
    "Handle check at main.lua:117: if swingTimer > 0 then",
    "Handle check at main.lua:126: if pickTimer > 0 then",
    "Handle check at main.lua:140: if rottimer > 0 then"
  ]
}