{
  "mod_name": "RMW - Desert Eagle",
  "mod_type": "tool",
  "current_version": 1,
  "scripts": [
    {
      "file": "main.lua",
      "lines": 709,
      "callbacks_found": [
        "SpentCasing",
        "init",
        "rndVec",
        "rnd",
        "approach",
        "rndRange",
        "AddRecoil",
        "ApplyRecoilTick",
        "yVisualGunRecoil(dt,",
        "uteFireRay(spr",
        "(dt)",
        "()\n\n"
      ],
      "api_calls": [
        {
          "function": "LoadSound",
          "line": 10,
          "domain": "client",
          "needs_player_id": false,
          "restricted_to": null,
          "deprecated": null
        },
        {
          "function": "LoadSound",
          "line": 11,
          "domain": "client",
          "needs_player_id": false,
          "restricted_to": null,
          "deprecated": null
        },
        {
          "function": "LoadSound",
          "line": 12,
          "domain": "client",
          "needs_player_id": false,
          "restricted_to": null,
          "deprecated": null
        },
        {
          "function": "LoadSound",
          "line": 13,
          "domain": "client",
          "needs_player_id": false,
          "restricted_to": null,
          "deprecated": null
        },
        {
          "function": "GetBodyTransform",
          "line": 44,
          "domain": "both",
          "needs_player_id": false,
          "restricted_to": null,
          "deprecated": null
        },
        {
          "function": "TransformToParentPoint",
          "line": 45,
          "domain": "both",
          "needs_player_id": false,
          "restricted_to": null,
          "deprecated": null
        },
        {
          "function": "Vec",
          "line": 45,
          "domain": "both",
          "needs_player_id": false,
          "restricted_to": null,
          "deprecated": null
        },
        {
          "function": "TransformToParentPoint",
          "line": 46,
          "domain": "both",
          "needs_player_id": false,
          "restricted_to": null,
          "deprecated": null
        },
        {
          "function": "Vec",
          "line": 46,
          "domain": "both",
          "needs_player_id": false,
          "restricted_to": null,
          "deprecated": null
        },
        {
          "function": "VecAdd",
          "line": 47,
          "domain": "both",
          "needs_player_id": false,
          "restricted_to": null,
          "deprecated": null
        },
        {
          "function": "GetPlayerVelocity",
          "line": 47,
          "domain": "server",
          "needs_player_id": true,
          "restricted_to": null,
          "deprecated": null
        },
        {
          "function": "VecSub",
          "line": 47,
          "domain": "both",
          "needs_player_id": false,
          "restricted_to": null,
          "deprecated": null
        },
        {
          "function": "Transform",
          "line": 48,
          "domain": "both",
          "needs_player_id": false,
          "restricted_to": null,
          "deprecated": null
        },
        {
          "function": "QuatEuler",
          "line": 48,
          "domain": "both",
          "needs_player_id": false,
          "restricted_to": null,
          "deprecated": null
        },
        {
          "function": "SetBodyVelocity",
          "line": 49,
          "domain": "both",
          "needs_player_id": false,
          "restricted_to": null,
          "deprecated": null
        },
        {
          "function": "RegisterTool",
          "line": 54,
          "domain": "server",
          "needs_player_id": false,
          "restricted_to": null,
          "deprecated": null
        },
        {
          "function": "SetBool",
          "line": 55,
          "domain": "both",
          "needs_player_id": false,
          "restricted_to": null,
          "deprecated": null
        },
        {
          "function": "GetBool",
          "line": 66,
          "domain": "both",
          "needs_player_id": false,
          "restricted_to": null,
          "deprecated": null
        },
        {
          "function": "LoadSound",
          "line": 86,
          "domain": "client",
          "needs_player_id": false,
          "restricted_to": null,
          "deprecated": null
        },
        {
          "function": "Vec",
          "line": 94,
          "domain": "both",
          "needs_player_id": false,
          "restricted_to": null,
          "deprecated": null
        },
        {
          "function": "VecNormalize",
          "line": 100,
          "domain": "both",
          "needs_player_id": false,
          "restricted_to": null,
          "deprecated": null
        },
        {
          "function": "Vec",
          "line": 100,
          "domain": "both",
          "needs_player_id": false,
          "restricted_to": null,
          "deprecated": null
        },
        {
          "function": "VecScale",
          "line": 101,
          "domain": "both",
          "needs_player_id": false,
          "restricted_to": null,
          "deprecated": null
        },
        {
          "function": "GetBool",
          "line": 133,
          "domain": "both",
          "needs_player_id": false,
          "restricted_to": null,
          "deprecated": null
        },
        {
          "function": "Transform",
          "line": 136,
          "domain": "both",
          "needs_player_id": false,
          "restricted_to": null,
          "deprecated": null
        },
        {
          "function": "Vec",
          "line": 136,
          "domain": "both",
          "needs_player_id": false,
          "restricted_to": null,
          "deprecated": null
        },
        {
          "function": "QuatEuler",
          "line": 136,
          "domain": "both",
          "needs_player_id": false,
          "restricted_to": null,
          "deprecated": null
        },
        {
          "function": "Transform",
          "line": 138,
          "domain": "both",
          "needs_player_id": false,
          "restricted_to": null,
          "deprecated": null
        },
        {
          "function": "Vec",
          "line": 138,
          "domain": "both",
          "needs_player_id": false,
          "restricted_to": null,
          "deprecated": null
        },
        {
          "function": "QuatEuler",
          "line": 138,
          "domain": "both",
          "needs_player_id": false,
          "restricted_to": null,
          "deprecated": null
        }
      ],
      "server_calls": 2,
      "client_calls": 5,
      "ambiguous_calls": 23,
      "deprecated_calls": [],
      "entity_handle_checks": [
        {
          "line": 236,
          "content": "if charginghandletime > 0 then ---Charginghandle"
        },
        {
          "line": 443,
          "content": "if GetBool(\"game.player.canusetool\") and InputDown(\"usetool\") and not attachmentmenu and GetInt(\"game.tool.gun.ammo\") > 0 and magazine > 0 and not low and fireswitch and not reloading and semi < 1 then"
        },
        {
          "line": 490,
          "content": "if GetBool(\"game.player.canusetool\") and InputDown(\"usetool\") and not attachmentmenu and not reloading and GetInt(\"game.tool.gun.ammo\") > 0 and not low and magazine > 0 and not fireswitch then"
        },
        {
          "line": 531,
          "content": "if InputDown(\"usetool\") and magazine > 0 then"
        },
        {
          "line": 532,
          "content": "if smoke > 0 then"
        }
      ],
      "registry_usage": [
        {
          "function": "SetBool",
          "line": 55,
          "domain": "both",
          "needs_player_id": false,
          "restricted_to": null,
          "deprecated": null
        },
        {
          "function": "GetBool",
          "line": 66,
          "domain": "both",
          "needs_player_id": false,
          "restricted_to": null,
          "deprecated": null
        },
        {
          "function": "GetBool",
          "line": 133,
          "domain": "both",
          "needs_player_id": false,
          "restricted_to": null,
          "deprecated": null
        }
      ]
    },
    {
      "file": "options.lua",
      "lines": 58,
      "callbacks_found": [
        "init",
        "draw",
        "optionsSlider",
        "round"
      ],
      "api_calls": [
        {
          "function": "GetBool",
          "line": 2,
          "domain": "both",
          "needs_player_id": false,
          "restricted_to": null,
          "deprecated": null
        },
        {
          "function": "UiTranslate",
          "line": 7,
          "domain": "client",
          "needs_player_id": false,
          "restricted_to": "client.draw",
          "deprecated": null
        },
        {
          "function": "UiCenter",
          "line": 7,
          "domain": "client",
          "needs_player_id": false,
          "restricted_to": "client.draw",
          "deprecated": null
        },
        {
          "function": "UiAlign",
          "line": 8,
          "domain": "client",
          "needs_player_id": false,
          "restricted_to": "client.draw",
          "deprecated": null
        },
        {
          "function": "UiFont",
          "line": 10,
          "domain": "client",
          "needs_player_id": false,
          "restricted_to": "client.draw",
          "deprecated": null
        },
        {
          "function": "UiText",
          "line": 11,
          "domain": "client",
          "needs_player_id": false,
          "restricted_to": "client.draw",
          "deprecated": null
        },
        {
          "function": "UiFont",
          "line": 12,
          "domain": "client",
          "needs_player_id": false,
          "restricted_to": "client.draw",
          "deprecated": null
        },
        {
          "function": "UiTranslate",
          "line": 13,
          "domain": "client",
          "needs_player_id": false,
          "restricted_to": "client.draw",
          "deprecated": null
        },
        {
          "function": "UiPush",
          "line": 14,
          "domain": "client",
          "needs_player_id": false,
          "restricted_to": "client.draw",
          "deprecated": null
        },
        {
          "function": "UiText",
          "line": 15,
          "domain": "client",
          "needs_player_id": false,
          "restricted_to": "client.draw",
          "deprecated": null
        },
        {
          "function": "UiTranslate",
          "line": 16,
          "domain": "client",
          "needs_player_id": false,
          "restricted_to": "client.draw",
          "deprecated": null
        },
        {
          "function": "UiAlign",
          "line": 17,
          "domain": "client",
          "needs_player_id": false,
          "restricted_to": "client.draw",
          "deprecated": null
        },
        {
          "function": "UiColor",
          "line": 18,
          "domain": "client",
          "needs_player_id": false,
          "restricted_to": "client.draw",
          "deprecated": null
        },
        {
          "function": "SetBool",
          "line": 22,
          "domain": "both",
          "needs_player_id": false,
          "restricted_to": null,
          "deprecated": null
        },
        {
          "function": "SetBool",
          "line": 27,
          "domain": "both",
          "needs_player_id": false,
          "restricted_to": null,
          "deprecated": null
        },
        {
          "function": "UiPop",
          "line": 30,
          "domain": "client",
          "needs_player_id": false,
          "restricted_to": "client.draw",
          "deprecated": null
        },
        {
          "function": "UiTranslate",
          "line": 34,
          "domain": "client",
          "needs_player_id": false,
          "restricted_to": "client.draw",
          "deprecated": null
        },
        {
          "function": "UiColor",
          "line": 41,
          "domain": "client",
          "needs_player_id": false,
          "restricted_to": "client.draw",
          "deprecated": null
        },
        {
          "function": "UiPush",
          "line": 42,
          "domain": "client",
          "needs_player_id": false,
          "restricted_to": "client.draw",
          "deprecated": null
        },
        {
          "function": "UiTranslate",
          "line": 43,
          "domain": "client",
          "needs_player_id": false,
          "restricted_to": "client.draw",
          "deprecated": null
        },
        {
          "function": "UiRect",
          "line": 46,
          "domain": "client",
          "needs_player_id": false,
          "restricted_to": "client.draw",
          "deprecated": null
        },
        {
          "function": "UiAlign",
          "line": 47,
          "domain": "client",
          "needs_player_id": false,
          "restricted_to": "client.draw",
          "deprecated": null
        },
        {
          "function": "UiTranslate",
          "line": 48,
          "domain": "client",
          "needs_player_id": false,
          "restricted_to": "client.draw",
          "deprecated": null
        },
        {
          "function": "UiSlider",
          "line": 49,
          "domain": "client",
          "needs_player_id": false,
          "restricted_to": "client.draw",
          "deprecated": null
        },
        {
          "function": "UiPop",
          "line": 51,
          "domain": "client",
          "needs_player_id": false,
          "restricted_to": "client.draw",
          "deprecated": null
        }
      ],
      "server_calls": 0,
      "client_calls": 22,
      "ambiguous_calls": 3,
      "deprecated_calls": [],
      "entity_handle_checks": [],
      "registry_usage": [
        {
          "function": "GetBool",
          "line": 2,
          "domain": "both",
          "needs_player_id": false,
          "restricted_to": null,
          "deprecated": null
        },
        {
          "function": "SetBool",
          "line": 22,
          "domain": "both",
          "needs_player_id": false,
          "restricted_to": null,
          "deprecated": null
        },
        {
          "function": "SetBool",
          "line": 27,
          "domain": "both",
          "needs_player_id": false,
          "restricted_to": null,
          "deprecated": null
        }
      ]
    },
    {
      "file": "safe.lua",
      "lines": 489,
      "callbacks_found": [
        "SpentCasing",
        "init",
        "rndVec",
        "rnd",
        "tick",
        "draw"
      ],
      "api_calls": [
        {
          "function": "LoadSound",
          "line": 10,
          "domain": "client",
          "needs_player_id": false,
          "restricted_to": null,
          "deprecated": null
        },
        {
          "function": "LoadSound",
          "line": 11,
          "domain": "client",
          "needs_player_id": false,
          "restricted_to": null,
          "deprecated": null
        },
        {
          "function": "LoadSound",
          "line": 12,
          "domain": "client",
          "needs_player_id": false,
          "restricted_to": null,
          "deprecated": null
        },
        {
          "function": "LoadSound",
          "line": 13,
          "domain": "client",
          "needs_player_id": false,
          "restricted_to": null,
          "deprecated": null
        },
        {
          "function": "GetBodyTransform",
          "line": 20,
          "domain": "both",
          "needs_player_id": false,
          "restricted_to": null,
          "deprecated": null
        },
        {
          "function": "TransformToParentPoint",
          "line": 21,
          "domain": "both",
          "needs_player_id": false,
          "restricted_to": null,
          "deprecated": null
        },
        {
          "function": "Vec",
          "line": 21,
          "domain": "both",
          "needs_player_id": false,
          "restricted_to": null,
          "deprecated": null
        },
        {
          "function": "TransformToParentPoint",
          "line": 22,
          "domain": "both",
          "needs_player_id": false,
          "restricted_to": null,
          "deprecated": null
        },
        {
          "function": "Vec",
          "line": 22,
          "domain": "both",
          "needs_player_id": false,
          "restricted_to": null,
          "deprecated": null
        },
        {
          "function": "VecAdd",
          "line": 23,
          "domain": "both",
          "needs_player_id": false,
          "restricted_to": null,
          "deprecated": null
        },
        {
          "function": "GetPlayerVelocity",
          "line": 23,
          "domain": "server",
          "needs_player_id": true,
          "restricted_to": null,
          "deprecated": null
        },
        {
          "function": "VecSub",
          "line": 23,
          "domain": "both",
          "needs_player_id": false,
          "restricted_to": null,
          "deprecated": null
        },
        {
          "function": "Transform",
          "line": 24,
          "domain": "both",
          "needs_player_id": false,
          "restricted_to": null,
          "deprecated": null
        },
        {
          "function": "QuatEuler",
          "line": 24,
          "domain": "both",
          "needs_player_id": false,
          "restricted_to": null,
          "deprecated": null
        },
        {
          "function": "SetBodyVelocity",
          "line": 25,
          "domain": "both",
          "needs_player_id": false,
          "restricted_to": null,
          "deprecated": null
        },
        {
          "function": "RegisterTool",
          "line": 30,
          "domain": "server",
          "needs_player_id": false,
          "restricted_to": null,
          "deprecated": null
        },
        {
          "function": "SetBool",
          "line": 31,
          "domain": "both",
          "needs_player_id": false,
          "restricted_to": null,
          "deprecated": null
        },
        {
          "function": "GetBool",
          "line": 42,
          "domain": "both",
          "needs_player_id": false,
          "restricted_to": null,
          "deprecated": null
        },
        {
          "function": "GetFloat",
          "line": 50,
          "domain": "both",
          "needs_player_id": false,
          "restricted_to": null,
          "deprecated": null
        },
        {
          "function": "SetFloat",
          "line": 52,
          "domain": "both",
          "needs_player_id": false,
          "restricted_to": null,
          "deprecated": null
        },
        {
          "function": "LoadSound",
          "line": 56,
          "domain": "client",
          "needs_player_id": false,
          "restricted_to": null,
          "deprecated": null
        },
        {
          "function": "Vec",
          "line": 64,
          "domain": "both",
          "needs_player_id": false,
          "restricted_to": null,
          "deprecated": null
        },
        {
          "function": "VecNormalize",
          "line": 70,
          "domain": "both",
          "needs_player_id": false,
          "restricted_to": null,
          "deprecated": null
        },
        {
          "function": "Vec",
          "line": 70,
          "domain": "both",
          "needs_player_id": false,
          "restricted_to": null,
          "deprecated": null
        },
        {
          "function": "VecScale",
          "line": 71,
          "domain": "both",
          "needs_player_id": false,
          "restricted_to": null,
          "deprecated": null
        },
        {
          "function": "GetString",
          "line": 82,
          "domain": "both",
          "needs_player_id": false,
          "restricted_to": null,
          "deprecated": null
        },
        {
          "function": "InputDown",
          "line": 106,
          "domain": "client",
          "needs_player_id": false,
          "restricted_to": null,
          "deprecated": null
        },
        {
          "function": "InputPressed",
          "line": 115,
          "domain": "client",
          "needs_player_id": false,
          "restricted_to": null,
          "deprecated": null
        },
        {
          "function": "PlaySound",
          "line": 117,
          "domain": "client",
          "needs_player_id": false,
          "restricted_to": null,
          "deprecated": null
        },
        {
          "function": "InputPressed",
          "line": 121,
          "domain": "client",
          "needs_player_id": false,
          "restricted_to": null,
          "deprecated": null
        },
        {
          "function": "PlaySound",
          "line": 123,
          "domain": "client",
          "needs_player_id": false,
          "restricted_to": null,
          "deprecated": null
        },
        {
          "function": "InputPressed",
          "line": 126,
          "domain": "client",
          "needs_player_id": false,
          "restricted_to": null,
          "deprecated": null
        },
        {
          "function": "InputPressed",
          "line": 130,
          "domain": "client",
          "needs_player_id": false,
          "restricted_to": null,
          "deprecated": null
        },
        {
          "function": "InputPressed",
          "line": 134,
          "domain": "client",
          "needs_player_id": false,
          "restricted_to": null,
          "deprecated": null
        },
        {
          "function": "InputPressed",
          "line": 138,
          "domain": "client",
          "needs_player_id": false,
          "restricted_to": null,
          "deprecated": null
        },
        {
          "function": "GetString",
          "line": 142,
          "domain": "both",
          "needs_player_id": false,
          "restricted_to": null,
          "deprecated": null
        },
        {
          "function": "Transform",
          "line": 150,
          "domain": "both",
          "needs_player_id": false,
          "restricted_to": null,
          "deprecated": null
        },
        {
          "function": "Vec",
          "line": 150,
          "domain": "both",
          "needs_player_id": false,
          "restricted_to": null,
          "deprecated": null
        },
        {
          "function": "QuatEuler",
          "line": 150,
          "domain": "both",
          "needs_player_id": false,
          "restricted_to": null,
          "deprecated": null
        },
        {
          "function": "Transform",
          "line": 154,
          "domain": "both",
          "needs_player_id": false,
          "restricted_to": null,
          "deprecated": null
        },
        {
          "function": "Vec",
          "line": 154,
          "domain": "both",
          "needs_player_id": false,
          "restricted_to": null,
          "deprecated": null
        },
        {
          "function": "QuatEuler",
          "line": 154,
          "domain": "both",
          "needs_player_id": false,
          "restricted_to": null,
          "deprecated": null
        },
        {
          "function": "Transform",
          "line": 160,
          "domain": "both",
          "needs_player_id": false,
          "restricted_to": null,
          "deprecated": null
        },
        {
          "function": "Vec",
          "line": 160,
          "domain": "both",
          "needs_player_id": false,
          "restricted_to": null,
          "deprecated": null
        },
        {
          "function": "QuatEuler",
          "line": 160,
          "domain": "both",
          "needs_player_id": false,
          "restricted_to": null,
          "deprecated": null
        },
        {
          "function": "Transform",
          "line": 164,
          "domain": "both",
          "needs_player_id": false,
          "restricted_to": null,
          "deprecated": null
        },
        {
          "function": "Vec",
          "line": 164,
          "domain": "both",
          "needs_player_id": false,
          "restricted_to": null,
          "deprecated": null
        },
        {
          "function": "QuatEuler",
          "line": 164,
          "domain": "both",
          "needs_player_id": false,
          "restricted_to": null,
          "deprecated": null
        },
        {
          "function": "Transform",
          "line": 170,
          "domain": "both",
          "needs_player_id": false,
          "restricted_to": null,
          "deprecated": null
        },
        {
          "function": "Vec",
          "line": 170,
          "domain": "both",
          "needs_player_id": false,
          "restricted_to": null,
          "deprecated": null
        },
        {
          "function": "QuatEuler",
          "line": 170,
          "domain": "both",
          "needs_player_id": false,
          "restricted_to": null,
          "deprecated": null
        },
        {
          "function": "Transform",
          "line": 174,
          "domain": "both",
          "needs_player_id": false,
          "restricted_to": null,
          "deprecated": null
        },
        {
          "function": "Vec",
          "line": 174,
          "domain": "both",
          "needs_player_id": false,
          "restricted_to": null,
          "deprecated": null
        },
        {
          "function": "QuatEuler",
          "line": 174,
          "domain": "both",
          "needs_player_id": false,
          "restricted_to": null,
          "deprecated": null
        },
        {
          "function": "Transform",
          "line": 192,
          "domain": "both",
          "needs_player_id": false,
          "restricted_to": null,
          "deprecated": null
        },
        {
          "function": "Vec",
          "line": 192,
          "domain": "both",
          "needs_player_id": false,
          "restricted_to": null,
          "deprecated": null
        },
        {
          "function": "QuatEuler",
          "line": 192,
          "domain": "both",
          "needs_player_id": false,
          "restricted_to": null,
          "deprecated": null
        },
        {
          "function": "Transform",
          "line": 201,
          "domain": "both",
          "needs_player_id": false,
          "restricted_to": null,
          "deprecated": null
        },
        {
          "function": "Vec",
          "line": 201,
          "domain": "both",
          "needs_player_id": false,
          "restricted_to": null,
          "deprecated": null
        },
        {
          "function": "QuatEuler",
          "line": 201,
          "domain": "both",
          "needs_player_id": false,
          "restricted_to": null,
          "deprecated": null
        },
        {
          "function": "InputDown",
          "line": 233,
          "domain": "client",
          "needs_player_id": false,
          "restricted_to": null,
          "deprecated": null
        },
        {
          "function": "InputPressed",
          "line": 253,
          "domain": "client",
          "needs_player_id": false,
          "restricted_to": null,
          "deprecated": null
        },
        {
          "function": "InputDown",
          "line": 253,
          "domain": "client",
          "needs_player_id": false,
          "restricted_to": null,
          "deprecated": null
        },
        {
          "function": "PlaySound",
          "line": 255,
          "domain": "client",
          "needs_player_id": false,
          "restricted_to": null,
          "deprecated": null
        },
        {
          "function": "PlaySound",
          "line": 262,
          "domain": "client",
          "needs_player_id": false,
          "restricted_to": null,
          "deprecated": null
        },
        {
          "function": "GetBool",
          "line": 283,
          "domain": "both",
          "needs_player_id": false,
          "restricted_to": null,
          "deprecated": null
        },
        {
          "function": "InputDown",
          "line": 283,
          "domain": "client",
          "needs_player_id": false,
          "restricted_to": null,
          "deprecated": null
        },
        {
          "function": "GetInt",
          "line": 283,
          "domain": "both",
          "needs_player_id": false,
          "restricted_to": null,
          "deprecated": null
        },
        {
          "function": "VecAdd",
          "line": 288,
          "domain": "both",
          "needs_player_id": false,
          "restricted_to": null,
          "deprecated": null
        },
        {
          "function": "Shoot",
          "line": 289,
          "domain": "both",
          "needs_player_id": false,
          "restricted_to": null,
          "deprecated": null
        },
        {
          "function": "Shoot",
          "line": 290,
          "domain": "both",
          "needs_player_id": false,
          "restricted_to": null,
          "deprecated": null
        },
        {
          "function": "PlaySound",
          "line": 300,
          "domain": "client",
          "needs_player_id": false,
          "restricted_to": null,
          "deprecated": null
        },
        {
          "function": "PlaySound",
          "line": 302,
          "domain": "client",
          "needs_player_id": false,
          "restricted_to": null,
          "deprecated": null
        },
        {
          "function": "SetInt",
          "line": 307,
          "domain": "both",
          "needs_player_id": false,
          "restricted_to": null,
          "deprecated": null
        },
        {
          "function": "GetInt",
          "line": 307,
          "domain": "both",
          "needs_player_id": false,
          "restricted_to": null,
          "deprecated": null
        },
        {
          "function": "GetBool",
          "line": 316,
          "domain": "both",
          "needs_player_id": false,
          "restricted_to": null,
          "deprecated": null
        },
        {
          "function": "InputDown",
          "line": 316,
          "domain": "client",
          "needs_player_id": false,
          "restricted_to": null,
          "deprecated": null
        },
        {
          "function": "GetInt",
          "line": 316,
          "domain": "both",
          "needs_player_id": false,
          "restricted_to": null,
          "deprecated": null
        },
        {
          "function": "VecAdd",
          "line": 321,
          "domain": "both",
          "needs_player_id": false,
          "restricted_to": null,
          "deprecated": null
        },
        {
          "function": "Shoot",
          "line": 322,
          "domain": "both",
          "needs_player_id": false,
          "restricted_to": null,
          "deprecated": null
        },
        {
          "function": "Shoot",
          "line": 323,
          "domain": "both",
          "needs_player_id": false,
          "restricted_to": null,
          "deprecated": null
        },
        {
          "function": "PlaySound",
          "line": 333,
          "domain": "client",
          "needs_player_id": false,
          "restricted_to": null,
          "deprecated": null
        },
        {
          "function": "PlaySound",
          "line": 335,
          "domain": "client",
          "needs_player_id": false,
          "restricted_to": null,
          "deprecated": null
        },
        {
          "function": "SetInt",
          "line": 340,
          "domain": "both",
          "needs_player_id": false,
          "restricted_to": null,
          "deprecated": null
        },
        {
          "function": "GetInt",
          "line": 340,
          "domain": "both",
          "needs_player_id": false,
          "restricted_to": null,
          "deprecated": null
        },
        {
          "function": "InputDown",
          "line": 349,
          "domain": "client",
          "needs_player_id": false,
          "restricted_to": null,
          "deprecated": null
        },
        {
          "function": "TransformToParentVec",
          "line": 353,
          "domain": "both",
          "needs_player_id": false,
          "restricted_to": null,
          "deprecated": null
        },
        {
          "function": "Vec",
          "line": 353,
          "domain": "both",
          "needs_player_id": false,
          "restricted_to": null,
          "deprecated": null
        },
        {
          "function": "VecScale",
          "line": 354,
          "domain": "both",
          "needs_player_id": false,
          "restricted_to": null,
          "deprecated": null
        },
        {
          "function": "ParticleColor",
          "line": 357,
          "domain": "client",
          "needs_player_id": false,
          "restricted_to": null,
          "deprecated": null
        },
        {
          "function": "VecAdd",
          "line": 358,
          "domain": "both",
          "needs_player_id": false,
          "restricted_to": null,
          "deprecated": null
        },
        {
          "function": "Vec",
          "line": 358,
          "domain": "both",
          "needs_player_id": false,
          "restricted_to": null,
          "deprecated": null
        },
        {
          "function": "ParticleType",
          "line": 359,
          "domain": "client",
          "needs_player_id": false,
          "restricted_to": null,
          "deprecated": null
        },
        {
          "function": "ParticleEmissive",
          "line": 360,
          "domain": "client",
          "needs_player_id": false,
          "restricted_to": null,
          "deprecated": null
        },
        {
          "function": "ParticleRadius",
          "line": 361,
          "domain": "client",
          "needs_player_id": false,
          "restricted_to": null,
          "deprecated": null
        },
        {
          "function": "ParticleDrag",
          "line": 362,
          "domain": "client",
          "needs_player_id": false,
          "restricted_to": null,
          "deprecated": null
        },
        {
          "function": "ParticleAlpha",
          "line": 363,
          "domain": "client",
          "needs_player_id": false,
          "restricted_to": null,
          "deprecated": null
        },
        {
          "function": "ParticleCollide",
          "line": 364,
          "domain": "client",
          "needs_player_id": false,
          "restricted_to": null,
          "deprecated": null
        },
        {
          "function": "SpawnParticle",
          "line": 365,
          "domain": "client",
          "needs_player_id": false,
          "restricted_to": null,
          "deprecated": null
        },
        {
          "function": "VecAdd",
          "line": 365,
          "domain": "both",
          "needs_player_id": false,
          "restricted_to": null,
          "deprecated": null
        },
        {
          "function": "Transform",
          "line": 379,
          "domain": "both",
          "needs_player_id": false,
          "restricted_to": null,
          "deprecated": null
        },
        {
          "function": "VecScale",
          "line": 379,
          "domain": "both",
          "needs_player_id": false,
          "restricted_to": null,
          "deprecated": null
        },
        {
          "function": "Vec",
          "line": 379,
          "domain": "both",
          "needs_player_id": false,
          "restricted_to": null,
          "deprecated": null
        },
        {
          "function": "GetBodyTransform",
          "line": 381,
          "domain": "both",
          "needs_player_id": false,
          "restricted_to": null,
          "deprecated": null
        },
        {
          "function": "TransformToParentVec",
          "line": 384,
          "domain": "both",
          "needs_player_id": false,
          "restricted_to": null,
          "deprecated": null
        },
        {
          "function": "Vec",
          "line": 384,
          "domain": "both",
          "needs_player_id": false,
          "restricted_to": null,
          "deprecated": null
        },
        {
          "function": "QueryRaycast",
          "line": 385,
          "domain": "both",
          "needs_player_id": false,
          "restricted_to": null,
          "deprecated": null
        },
        {
          "function": "VecAdd",
          "line": 386,
          "domain": "both",
          "needs_player_id": false,
          "restricted_to": null,
          "deprecated": null
        },
        {
          "function": "VecScale",
          "line": 386,
          "domain": "both",
          "needs_player_id": false,
          "restricted_to": null,
          "deprecated": null
        },
        {
          "function": "TransformToParentVec",
          "line": 391,
          "domain": "both",
          "needs_player_id": false,
          "restricted_to": null,
          "deprecated": null
        },
        {
          "function": "Vec",
          "line": 391,
          "domain": "both",
          "needs_player_id": false,
          "restricted_to": null,
          "deprecated": null
        },
        {
          "function": "QueryRaycast",
          "line": 392,
          "domain": "both",
          "needs_player_id": false,
          "restricted_to": null,
          "deprecated": null
        },
        {
          "function": "VecAdd",
          "line": 393,
          "domain": "both",
          "needs_player_id": false,
          "restricted_to": null,
          "deprecated": null
        },
        {
          "function": "VecScale",
          "line": 393,
          "domain": "both",
          "needs_player_id": false,
          "restricted_to": null,
          "deprecated": null
        },
        {
          "function": "TransformToParentVec",
          "line": 398,
          "domain": "both",
          "needs_player_id": false,
          "restricted_to": null,
          "deprecated": null
        },
        {
          "function": "Vec",
          "line": 398,
          "domain": "both",
          "needs_player_id": false,
          "restricted_to": null,
          "deprecated": null
        },
        {
          "function": "QueryRaycast",
          "line": 399,
          "domain": "both",
          "needs_player_id": false,
          "restricted_to": null,
          "deprecated": null
        },
        {
          "function": "VecAdd",
          "line": 400,
          "domain": "both",
          "needs_player_id": false,
          "restricted_to": null,
          "deprecated": null
        },
        {
          "function": "VecScale",
          "line": 400,
          "domain": "both",
          "needs_player_id": false,
          "restricted_to": null,
          "deprecated": null
        },
        {
          "function": "Transform",
          "line": 406,
          "domain": "both",
          "needs_player_id": false,
          "restricted_to": null,
          "deprecated": null
        },
        {
          "function": "Transform",
          "line": 409,
          "domain": "both",
          "needs_player_id": false,
          "restricted_to": null,
          "deprecated": null
        },
        {
          "function": "Vec",
          "line": 409,
          "domain": "both",
          "needs_player_id": false,
          "restricted_to": null,
          "deprecated": null
        },
        {
          "function": "QuatEuler",
          "line": 409,
          "domain": "both",
          "needs_player_id": false,
          "restricted_to": null,
          "deprecated": null
        },
        {
          "function": "Transform",
          "line": 413,
          "domain": "both",
          "needs_player_id": false,
          "restricted_to": null,
          "deprecated": null
        },
        {
          "function": "Vec",
          "line": 413,
          "domain": "both",
          "needs_player_id": false,
          "restricted_to": null,
          "deprecated": null
        },
        {
          "function": "QuatEuler",
          "line": 413,
          "domain": "both",
          "needs_player_id": false,
          "restricted_to": null,
          "deprecated": null
        },
        {
          "function": "Transform",
          "line": 418,
          "domain": "both",
          "needs_player_id": false,
          "restricted_to": null,
          "deprecated": null
        },
        {
          "function": "Vec",
          "line": 418,
          "domain": "both",
          "needs_player_id": false,
          "restricted_to": null,
          "deprecated": null
        },
        {
          "function": "QuatEuler",
          "line": 418,
          "domain": "both",
          "needs_player_id": false,
          "restricted_to": null,
          "deprecated": null
        },
        {
          "function": "Transform",
          "line": 423,
          "domain": "both",
          "needs_player_id": false,
          "restricted_to": null,
          "deprecated": null
        },
        {
          "function": "Vec",
          "line": 423,
          "domain": "both",
          "needs_player_id": false,
          "restricted_to": null,
          "deprecated": null
        },
        {
          "function": "QuatEuler",
          "line": 423,
          "domain": "both",
          "needs_player_id": false,
          "restricted_to": null,
          "deprecated": null
        },
        {
          "function": "GetString",
          "line": 436,
          "domain": "both",
          "needs_player_id": false,
          "restricted_to": null,
          "deprecated": null
        },
        {
          "function": "UiPush",
          "line": 437,
          "domain": "client",
          "needs_player_id": false,
          "restricted_to": "client.draw",
          "deprecated": null
        },
        {
          "function": "UiTranslate",
          "line": 438,
          "domain": "client",
          "needs_player_id": false,
          "restricted_to": "client.draw",
          "deprecated": null
        },
        {
          "function": "UiCenter",
          "line": 438,
          "domain": "client",
          "needs_player_id": false,
          "restricted_to": "client.draw",
          "deprecated": null
        },
        {
          "function": "UiHeight",
          "line": 438,
          "domain": "client",
          "needs_player_id": false,
          "restricted_to": "client.draw",
          "deprecated": null
        },
        {
          "function": "UiAlign",
          "line": 439,
          "domain": "client",
          "needs_player_id": false,
          "restricted_to": "client.draw",
          "deprecated": null
        },
        {
          "function": "UiColor",
          "line": 440,
          "domain": "client",
          "needs_player_id": false,
          "restricted_to": "client.draw",
          "deprecated": null
        },
        {
          "function": "UiFont",
          "line": 441,
          "domain": "client",
          "needs_player_id": false,
          "restricted_to": "client.draw",
          "deprecated": null
        },
        {
          "function": "UiText",
          "line": 443,
          "domain": "client",
          "needs_player_id": false,
          "restricted_to": "client.draw",
          "deprecated": null
        },
        {
          "function": "GetString",
          "line": 448,
          "domain": "both",
          "needs_player_id": false,
          "restricted_to": null,
          "deprecated": null
        },
        {
          "function": "UiPush",
          "line": 449,
          "domain": "client",
          "needs_player_id": false,
          "restricted_to": "client.draw",
          "deprecated": null
        },
        {
          "function": "UiTranslate",
          "line": 450,
          "domain": "client",
          "needs_player_id": false,
          "restricted_to": "client.draw",
          "deprecated": null
        },
        {
          "function": "UiCenter",
          "line": 450,
          "domain": "client",
          "needs_player_id": false,
          "restricted_to": "client.draw",
          "deprecated": null
        },
        {
          "function": "UiHeight",
          "line": 450,
          "domain": "client",
          "needs_player_id": false,
          "restricted_to": "client.draw",
          "deprecated": null
        },
        {
          "function": "UiAlign",
          "line": 451,
          "domain": "client",
          "needs_player_id": false,
          "restricted_to": "client.draw",
          "deprecated": null
        },
        {
          "function": "UiColor",
          "line": 452,
          "domain": "client",
          "needs_player_id": false,
          "restricted_to": "client.draw",
          "deprecated": null
        },
        {
          "function": "UiFont",
          "line": 453,
          "domain": "client",
          "needs_player_id": false,
          "restricted_to": "client.draw",
          "deprecated": null
        },
        {
          "function": "UiText",
          "line": 455,
          "domain": "client",
          "needs_player_id": false,
          "restricted_to": "client.draw",
          "deprecated": null
        },
        {
          "function": "GetString",
          "line": 459,
          "domain": "both",
          "needs_player_id": false,
          "restricted_to": null,
          "deprecated": null
        },
        {
          "function": "UiPush",
          "line": 460,
          "domain": "client",
          "needs_player_id": false,
          "restricted_to": "client.draw",
          "deprecated": null
        },
        {
          "function": "UiTranslate",
          "line": 461,
          "domain": "client",
          "needs_player_id": false,
          "restricted_to": "client.draw",
          "deprecated": null
        },
        {
          "function": "UiCenter",
          "line": 461,
          "domain": "client",
          "needs_player_id": false,
          "restricted_to": "client.draw",
          "deprecated": null
        },
        {
          "function": "UiHeight",
          "line": 461,
          "domain": "client",
          "needs_player_id": false,
          "restricted_to": "client.draw",
          "deprecated": null
        },
        {
          "function": "UiAlign",
          "line": 462,
          "domain": "client",
          "needs_player_id": false,
          "restricted_to": "client.draw",
          "deprecated": null
        },
        {
          "function": "UiColor",
          "line": 463,
          "domain": "client",
          "needs_player_id": false,
          "restricted_to": "client.draw",
          "deprecated": null
        },
        {
          "function": "UiFont",
          "line": 464,
          "domain": "client",
          "needs_player_id": false,
          "restricted_to": "client.draw",
          "deprecated": null
        },
        {
          "function": "UiText",
          "line": 466,
          "domain": "client",
          "needs_player_id": false,
          "restricted_to": "client.draw",
          "deprecated": null
        },
        {
          "function": "GetString",
          "line": 470,
          "domain": "both",
          "needs_player_id": false,
          "restricted_to": null,
          "deprecated": null
        },
        {
          "function": "UiPush",
          "line": 471,
          "domain": "client",
          "needs_player_id": false,
          "restricted_to": "client.draw",
          "deprecated": null
        },
        {
          "function": "UiTranslate",
          "line": 472,
          "domain": "client",
          "needs_player_id": false,
          "restricted_to": "client.draw",
          "deprecated": null
        },
        {
          "function": "UiCenter",
          "line": 472,
          "domain": "client",
          "needs_player_id": false,
          "restricted_to": "client.draw",
          "deprecated": null
        },
        {
          "function": "UiHeight",
          "line": 472,
          "domain": "client",
          "needs_player_id": false,
          "restricted_to": "client.draw",
          "deprecated": null
        },
        {
          "function": "UiAlign",
          "line": 473,
          "domain": "client",
          "needs_player_id": false,
          "restricted_to": "client.draw",
          "deprecated": null
        },
        {
          "function": "UiColor",
          "line": 474,
          "domain": "client",
          "needs_player_id": false,
          "restricted_to": "client.draw",
          "deprecated": null
        },
        {
          "function": "UiFont",
          "line": 475,
          "domain": "client",
          "needs_player_id": false,
          "restricted_to": "client.draw",
          "deprecated": null
        },
        {
          "function": "UiText",
          "line": 477,
          "domain": "client",
          "needs_player_id": false,
          "restricted_to": "client.draw",
          "deprecated": null
        }
      ],
      "server_calls": 2,
      "client_calls": 66,
      "ambiguous_calls": 100,
      "deprecated_calls": [],
      "entity_handle_checks": [
        {
          "line": 283,
          "content": "if GetBool(\"game.player.canusetool\") and InputDown(\"usetool\") and not attachmentmenu and GetInt(\"game.tool.gun.ammo\") > 0 and magazine > 0 and fireswitch and not reloading then"
        },
        {
          "line": 316,
          "content": "if GetBool(\"game.player.canusetool\") and InputDown(\"usetool\") and not attachmentmenu and not reloading and GetInt(\"game.tool.gun.ammo\") > 0 and magazine > 0 and not fireswitch then"
        },
        {
          "line": 349,
          "content": "if InputDown(\"usetool\") and magazine > 0 then"
        },
        {
          "line": 350,
          "content": "if smoke > 0 then"
        }
      ],
      "registry_usage": [
        {
          "function": "SetBool",
          "line": 31,
          "domain": "both",
          "needs_player_id": false,
          "restricted_to": null,
          "deprecated": null
        },
        {
          "function": "GetBool",
          "line": 42,
          "domain": "both",
          "needs_player_id": false,
          "restricted_to": null,
          "deprecated": null
        },
        {
          "function": "GetFloat",
          "line": 50,
          "domain": "both",
          "needs_player_id": false,
          "restricted_to": null,
          "deprecated": null
        },
        {
          "function": "SetFloat",
          "line": 52,
          "domain": "both",
          "needs_player_id": false,
          "restricted_to": null,
          "deprecated": null
        },
        {
          "function": "GetString",
          "line": 82,
          "domain": "both",
          "needs_player_id": false,
          "restricted_to": null,
          "deprecated": null
        },
        {
          "function": "GetString",
          "line": 142,
          "domain": "both",
          "needs_player_id": false,
          "restricted_to": null,
          "deprecated": null
        },
        {
          "function": "GetBool",
          "line": 283,
          "domain": "both",
          "needs_player_id": false,
          "restricted_to": null,
          "deprecated": null
        },
        {
          "function": "GetInt",
          "line": 283,
          "domain": "both",
          "needs_player_id": false,
          "restricted_to": null,
          "deprecated": null
        },
        {
          "function": "SetInt",
          "line": 307,
          "domain": "both",
          "needs_player_id": false,
          "restricted_to": null,
          "deprecated": null
        },
        {
          "function": "GetInt",
          "line": 307,
          "domain": "both",
          "needs_player_id": false,
          "restricted_to": null,
          "deprecated": null
        },
        {
          "function": "GetBool",
          "line": 316,
          "domain": "both",
          "needs_player_id": false,
          "restricted_to": null,
          "deprecated": null
        },
        {
          "function": "GetInt",
          "line": 316,
          "domain": "both",
          "needs_player_id": false,
          "restricted_to": null,
          "deprecated": null
        },
        {
          "function": "SetInt",
          "line": 340,
          "domain": "both",
          "needs_player_id": false,
          "restricted_to": null,
          "deprecated": null
        },
        {
          "function": "GetInt",
          "line": 340,
          "domain": "both",
          "needs_player_id": false,
          "restricted_to": null,
          "deprecated": null
        },
        {
          "function": "GetString",
          "line": 436,
          "domain": "both",
          "needs_player_id": false,
          "restricted_to": null,
          "deprecated": null
        },
        {
          "function": "GetString",
          "line": 448,
          "domain": "both",
          "needs_player_id": false,
          "restricted_to": null,
          "deprecated": null
        },
        {
          "function": "GetString",
          "line": 459,
          "domain": "both",
          "needs_player_id": false,
          "restricted_to": null,
          "deprecated": null
        },
        {
          "function": "GetString",
          "line": 470,
          "domain": "both",
          "needs_player_id": false,
          "restricted_to": null,
          "deprecated": null
        }
      ]
    }
  ],
  "complexity": "complex",
  "estimated_approach": "ai",
  "issues": [
    "Handle check at main.lua:236: if charginghandletime > 0 then ---Charginghandle",
    "Handle check at main.lua:443: if GetBool(\"game.player.canusetool\") and InputDown(\"usetool\") and not attachmentmenu and GetInt(\"game.tool.gun.ammo\") > 0 and magazine > 0 and not low and fireswitch and not reloading and semi < 1 then",
    "Handle check at main.lua:490: if GetBool(\"game.player.canusetool\") and InputDown(\"usetool\") and not attachmentmenu and not reloading and GetInt(\"game.tool.gun.ammo\") > 0 and not low and magazine > 0 and not fireswitch then",
    "Handle check at main.lua:531: if InputDown(\"usetool\") and magazine > 0 then",
    "Handle check at main.lua:532: if smoke > 0 then",
    "Handle check at safe.lua:283: if GetBool(\"game.player.canusetool\") and InputDown(\"usetool\") and not attachmentmenu and GetInt(\"game.tool.gun.ammo\") > 0 and magazine > 0 and fireswitch and not reloading then",
    "Handle check at safe.lua:316: if GetBool(\"game.player.canusetool\") and InputDown(\"usetool\") and not attachmentmenu and not reloading and GetInt(\"game.tool.gun.ammo\") > 0 and magazine > 0 and not fireswitch then",
    "Handle check at safe.lua:349: if InputDown(\"usetool\") and magazine > 0 then",
    "Handle check at safe.lua:350: if smoke > 0 then"
  ]
}